0010101__Decade_Counter_MOD_10/t_flipflop.v
module t_flipflop(
    input t,
    input clk,
    input preset,
    input clear,
    output reg q,
    output q_bar
);
    assign q_bar = ~q;

    always @(posedge clk, posedge preset, posedge clear) 
    begin
        if(preset) q<=1'b1;
        else if(clear) q<=1'b1;
        else q<=t^q;    
    end
endmodule

0010101__Decade_Counter_MOD_10/decade_counter_mod_ten.v
module decade_counter_mod_ten(
    input T,
    input clock,
    input preset,
    input clear,
    output [3:0] Q,
    output [3:0] Q_bar
);
    wire clk_b, clk_c, clk_d;
    wire auto_clear;
    wire clear_eff;

    assign auto_clear = Q[2] & ~Q[3] & Q[0] & ~Q[1];
    assign clear_eff = clear | auto_clear;

    assign clk_b = Q[0];
    t_flipflop m1(
        .t(T),
        .clk(clock),
        .preset(preset),
        .clear(clear_eff),
        .q(Q[0]),
        .q_bar(Q_bar[0])
    );

    assign clk_c = Q[1];
    t_flipflop m2(
        .t(T),
        .clk(clk_b),
        .preset(preset),
        .clear(clear_eff),
        .q(Q[1]),
        .q_bar(Q_bar[1])
    );
    
    assign clk_d = Q[2];
    t_flipflop m3(
        .t(T),
        .clk(clk_c),
        .preset(preset),
        .clear(clear_eff),
        .q(Q[2]),
        .q_bar(Q_bar[2])
    );
    
    t_flipflop m4(
        .t(T),
        .clk(clk_d),
        .preset(preset),
        .clear(clear_eff),
        .q(Q[3]),
        .q_bar(Q_bar[3])
    );

    
endmodule

0010101__Decade_Counter_MOD_10/decade_counter_mod_ten_tb.v
`timescale 10ps/1ps

module decade_counter_mod_ten_tb;
    reg clear, reset, t, clk;
    wire [3:0] Q;
    wire [3:0] Q_bar;

    decade_counter_mod_ten uut(
        .clock(clk),
        .clear(clear),
        .preset(reset),
        .T(t),
        .Q(Q),
        .Q_bar(Q_bar)
    );

    initial 
    begin
        clk = 0;
        forever #10 clk = ~clk;
    end

    initial
    begin
        $dumpfile("vcd_file.vcd");
        $dumpvars(0,decade_counter_mod_ten_tb);

        $monitor("Time : %0t | Clk : %b | Reset : %b | Clear : %b | T : %b | Q : %b",$time, clk, reset, clear, t, Q_bar);
        reset =1 ;t=0; 
        #10 reset = 0; clear = 0; t = 1;
        
        #300;
        #10 $finish;
    end
endmodule

0010101__Decade_Counter_MOD_10/vcd_file.vcd
$date
	Wed Jun 25 14:17:06 2025
$end
$version
	Icarus Verilog
$end
$timescale
	1ps
$end
$scope module decade_counter_mod_ten_tb $end
$var wire 4 ! Q_bar [3:0] $end
$var wire 4 " Q [3:0] $end
$var reg 1 # clear $end
$var reg 1 $ clk $end
$var reg 1 % reset $end
$var reg 1 & t $end
$scope module uut $end
$var wire 1 & T $end
$var wire 1 ' auto_clear $end
$var wire 1 # clear $end
$var wire 1 ( clear_eff $end
$var wire 1 $ clock $end
$var wire 1 % preset $end
$var wire 1 ) clk_d $end
$var wire 1 * clk_c $end
$var wire 1 + clk_b $end
$var wire 4 , Q_bar [3:0] $end
$var wire 4 - Q [3:0] $end
$scope module m1 $end
$var wire 1 ( clear $end
$var wire 1 $ clk $end
$var wire 1 % preset $end
$var wire 1 . q_bar $end
$var wire 1 & t $end
$var reg 1 / q $end
$upscope $end
$scope module m2 $end
$var wire 1 ( clear $end
$var wire 1 + clk $end
$var wire 1 % preset $end
$var wire 1 0 q_bar $end
$var wire 1 & t $end
$var reg 1 1 q $end
$upscope $end
$scope module m3 $end
$var wire 1 ( clear $end
$var wire 1 * clk $end
$var wire 1 % preset $end
$var wire 1 2 q_bar $end
$var wire 1 & t $end
$var reg 1 3 q $end
$upscope $end
$scope module m4 $end
$var wire 1 ( clear $end
$var wire 1 ) clk $end
$var wire 1 % preset $end
$var wire 1 4 q_bar $end
$var wire 1 & t $end
$var reg 1 5 q $end
$upscope $end
$upscope $end
$upscope $end
$enddefinitions $end
$comment Show the parameter values. $end
$dumpall
$end
#0
$dumpvars
15
04
13
02
11
00
1/
0.
b1111 -
b0 ,
1+
1*
1)
x(
0'
0&
1%
0$
x#
b1111 "
b0 !
$end
#100
b1 !
b1 ,
1.
0+
b1110 "
b1110 -
0/
0(
1&
0#
0%
1$
#200
0$
#300
10
0*
01
b10 !
b10 ,
0.
1+
b1101 "
b1101 -
1/
1$
#400
0$
#500
b11 !
b11 ,
1.
0+
b1100 "
b1100 -
0/
1$
#600
0$
#700
12
0)
03
00
1*
11
b100 !
b100 ,
0.
1+
b1011 "
b1011 -
1/
1$
#800
0$
#900
b101 !
b101 ,
1.
0+
b1010 "
b1010 -
0/
1$
#1000
0$
#1100
10
0*
01
b110 !
b110 ,
0.
1+
b1001 "
b1001 -
1/
1$
#1200
0$
#1300
b111 !
b111 ,
1.
0+
b1000 "
b1000 -
0/
1$
#1400
0$
#1500
14
05
02
1)
13
00
1*
11
b1000 !
b1000 ,
0.
1+
b111 "
b111 -
1/
1$
#1600
0$
#1700
b1001 !
b1001 ,
1.
0+
b110 "
b110 -
0/
1$
#1800
0$
#1900
04
15
0(
0'
00
1*
11
b0 !
b0 ,
0.
1+
b1111 "
b1111 -
1/
1$
#2000
0$
#2100
b1 !
b1 ,
1.
0+
b1110 "
b1110 -
0/
1$
#2200
0$
#2300
10
0*
01
b10 !
b10 ,
0.
1+
b1101 "
b1101 -
1/
1$
#2400
0$
#2500
b11 !
b11 ,
1.
0+
b1100 "
b1100 -
0/
1$
#2600
0$
#2700
12
0)
03
00
1*
11
b100 !
b100 ,
0.
1+
b1011 "
b1011 -
1/
1$
#2800
0$
#2900
b101 !
b101 ,
1.
0+
b1010 "
b1010 -
0/
1$
#3000
0$
#3100
10
0*
01
b110 !
b110 ,
0.
1+
b1001 "
b1001 -
1/
1$
