0001101__Parity_Generator_and_Checker/parity_generator_and_checker.v
//given a 4-bit original signal that is to be transmitted, now odd or even parity can be generated
//from the input noise, i will change the thvalue of bit at that location..

module parity_generator_and_checker(
    input [3:0] A,
    input [2:0] noise,
    output reg [4:0]even_parity,
    output reg [4:0] odd_parity,
    output reg noise_even_detected,
    output reg noise_odd_detected,
    output reg [4:0] noise_even,
    output reg [4:0] noise_odd
);
    wire t;

    

    assign t = ^A;
    always @(*) 
        begin
            if (t)
                begin
                    even_parity = {A,1'b1};
                    odd_parity = {A,1'b0}; 
                end
            else
                begin
                    even_parity = {A,1'b0};
                    odd_parity = {A,1'b1}; 
                end
        end
  
    always @(*) begin
        noise_even = even_parity;
        noise_odd  = odd_parity;

        if (noise < 5) begin
            noise_even[noise] = ~even_parity[noise];
            noise_odd[noise]  = ~odd_parity[noise];
        end
    end

    wire x1, x2;
    
    assign x1 = ^noise_even;
    assign x2 = ^noise_odd;

    always @(*) 
        begin
            if (x1) 
                begin
                    noise_even_detected = 1'b1;
                end
            else
                begin
                    noise_even_detected = 1'b0;
                end

            if (x2) 
                begin
                    noise_odd_detected = 1'b0;
                end
            else
                begin
                    noise_odd_detected = 1'b1;
                end
        end

endmodule

0001101__Parity_Generator_and_Checker/testbench.v
`timescale 1ns / 1ps

module parity_generator_and_checker_tb;

    reg [3:0] A;
    reg [2:0] noise;

    wire [4:0] even_parity;
    wire [4:0] odd_parity;
    wire noise_even_detected;
    wire noise_odd_detected;
    wire [4:0] noise_even;
    wire [4:0] noise_odd;

    parity_generator_and_checker uut (
        .A(A), 
        .noise(noise), 
        .even_parity(even_parity), 
        .odd_parity(odd_parity), 
        .noise_even_detected(noise_even_detected), 
        .noise_odd_detected(noise_odd_detected),
        .noise_even(noise_even),
        .noise_odd(noise_odd)
    );

    initial begin
        $dumpfile("parity_tb.vcd");
        $dumpvars(0, uut);

        $monitor("Time=%0t | A=%b noise=%d | even_parity=%b odd_parity=%b | noise_even=%b noise_odd=%b | even_error=%b odd_error=%b",
                 $time, A, noise, even_parity, odd_parity, noise_even, noise_odd, noise_even_detected, noise_odd_detected);

        #10 A = 4'b1010; noise = 3'd1;
        #10 A = 4'b1111; noise = 3'd2; 
        #10 A = 4'b0000; noise = 3'd1;
        #10 A = 4'b1011; noise = 3'd0; 
        #10 A = 4'b0110; noise = 3'd2; 
        #10 A = 4'b1100; noise = 3'd3; 
        #10 A = 4'b1001; noise = 3'd2; 
        #10 A = 4'b0011; noise = 3'd1;

        $finish;
    end

endmodule

0001101__Parity_Generator_and_Checker/parity_tb.vcd
$date
	Sat Jun 14 12:29:30 2025
$end
$version
	Icarus Verilog
$end
$timescale
	1ps
$end
$scope module parity_generator_and_checker_tb $end
$scope module uut $end
$var wire 4 ! A [3:0] $end
$var wire 3 " noise [2:0] $end
$var wire 1 # x2 $end
$var wire 1 $ x1 $end
$var wire 1 % t $end
$var reg 5 & even_parity [4:0] $end
$var reg 5 ' noise_even [4:0] $end
$var reg 1 ( noise_even_detected $end
$var reg 5 ) noise_odd [4:0] $end
$var reg 1 * noise_odd_detected $end
$var reg 5 + odd_parity [4:0] $end
$upscope $end
$upscope $end
$enddefinitions $end
$comment Show the parameter values. $end
$dumpall
$end
#0
$dumpvars
bx +
x*
bx )
x(
bx '
bx &
x%
x$
x#
bx "
bx !
$end
#10000
1*
1(
0#
b10111 )
1$
b10110 '
b10101 +
b10100 &
b1 "
0%
b1010 !
#20000
0#
b11011 )
1$
b11010 '
b11111 +
b11110 &
b10 "
b1111 !
#30000
0#
b11 )
1$
b10 '
b1 +
b0 &
b1 "
b0 !
#40000
0#
b10111 )
1$
b10110 '
b10110 +
b10111 &
b0 "
1%
b1011 !
#50000
0#
b1001 )
1$
b1000 '
b1101 +
b1100 &
b10 "
0%
b110 !
#60000
0#
b10001 )
1$
b10000 '
b11001 +
b11000 &
b11 "
b1100 !
#70000
0#
b10111 )
1$
b10110 '
b10011 +
b10010 &
b10 "
b1001 !
#80000
0#
b101 )
1$
b100 '
b111 +
b110 &
b1 "
b11 !
