0010010__JK_Flip_Flop_using_Logic_Gates/jk_flipflop.v
module jk_flip_flop_master_slave(Q, Qn, C, J, K, RESETn);
   output Q;
   output Qn;
   input  C;
   input  J;
   input  K;
   input  RESETn; // Active low reset signal.
   
   wire   MQ;  // The master's Q output.
   wire   MQn; // The master's Qn output.
   wire   Cn;  // The clock input to the slave shall be the complement of the master's.
   wire   J1;  
   wire   K1;  
   wire   J2;  // The actual input to the first SR latch (S).
   wire   K2;  // The actual input to the first SR latch (R).

   assign J2 = !RESETn ? 0 : J1;  // Upon reset force J2 = 0
   assign K2 = !RESETn ? 1 : K1;  // Upon reset force K2 = 1
   
   and(J1, J, Qn);
   and(K1, K, Q);   
   not(Cn, C);   
   sr_latch_gated master(MQ, MQn, C, J2, K2);
   sr_latch_gated slave(Q, Qn, Cn, MQ, MQn);   
endmodule 

module sr_latch_gated(Q, Qn, G, S, R);
   output Q;
   output Qn;
   input  G;   
   input  S;
   input  R;
   
   wire   S1;
   wire   R1;
   
   and(S1, G, S);
   and(R1, G, R);   
   nor(Qn, S1, Q);
   nor(Q, R1, Qn);
endmodule

0010010__JK_Flip_Flop_using_Logic_Gates/testbench.v
`timescale 1ns / 1ps

module tb_jk_flip_flop;

    reg C;
    reg J;
    reg K;
    reg RESETn;
    wire Q;
    wire Qn;

    jk_flip_flop_master_slave uut (
        .Q(Q),
        .Qn(Qn),
        .C(C),
        .J(J),
        .K(K),
        .RESETn(RESETn)
    );

    initial begin
        C = 0;
        forever #5 C = ~C;
    end

    initial begin
        $dumpfile("jk_ff.vcd");
        $dumpvars(0, tb_jk_flip_flop);

        J = 0; K = 0; RESETn = 0;
        #10;

        RESETn = 1;
        #10;

        J = 1; K = 0;
        #20;

        J = 0; K = 1;
        #20;

        J = 1; K = 1;
        #20;

        J = 0; K = 0;
        #20;

        J = 1; K = 0;
        #20;

        J = 0; K = 1;
        #20;

        J = 1; K = 1;
        #20;

        $finish;
    end

    initial begin
        $monitor("Time=%0t | RESETn=%b | C=%b | J=%b | K=%b | Q=%b | Qn=%b", 
                 $time, RESETn, C, J, K, Q, Qn);
    end

endmodule

0010010__JK_Flip_Flop_using_Logic_Gates/jk_ff.vcd
$date
	Thu Jun 19 13:58:59 2025
$end
$version
	Icarus Verilog
$end
$timescale
	1ps
$end
$scope module tb_jk_flip_flop $end
$var wire 1 ! Qn $end
$var wire 1 " Q $end
$var reg 1 # C $end
$var reg 1 $ J $end
$var reg 1 % K $end
$var reg 1 & RESETn $end
$scope module uut $end
$var wire 1 # C $end
$var wire 1 ' Cn $end
$var wire 1 $ J $end
$var wire 1 ( J1 $end
$var wire 1 % K $end
$var wire 1 ) K1 $end
$var wire 1 & RESETn $end
$var wire 1 ! Qn $end
$var wire 1 " Q $end
$var wire 1 * MQn $end
$var wire 1 + MQ $end
$var wire 1 , K2 $end
$var wire 1 - J2 $end
$scope module master $end
$var wire 1 # G $end
$var wire 1 + Q $end
$var wire 1 * Qn $end
$var wire 1 , R $end
$var wire 1 . R1 $end
$var wire 1 - S $end
$var wire 1 / S1 $end
$upscope $end
$scope module slave $end
$var wire 1 ' G $end
$var wire 1 " Q $end
$var wire 1 ! Qn $end
$var wire 1 * R $end
$var wire 1 0 R1 $end
$var wire 1 + S $end
$var wire 1 1 S1 $end
$upscope $end
$upscope $end
$upscope $end
$enddefinitions $end
$comment Show the parameter values. $end
$dumpall
$end
#0
$dumpvars
x1
x0
0/
0.
0-
1,
x+
x*
0)
0(
1'
0&
0%
0$
0#
x"
x!
$end
#5000
1*
01
00
0+
0'
1.
1#
#10000
1!
0"
10
0,
1'
0.
0#
1&
#15000
00
0'
1#
#20000
10
1-
1'
1(
0#
1$
#25000
1+
00
0*
0'
1/
1#
#30000
0-
1"
0(
0!
11
1'
0/
0#
#35000
01
0'
1#
#40000
1,
11
1'
1)
0#
1%
0$
#45000
1*
01
0+
0'
1.
1#
#50000
0,
1!
0)
0"
10
1'
0.
0#
#55000
00
0'
1#
#60000
10
1-
1'
1(
0#
1$
#65000
1+
00
0*
0'
1/
1#
#70000
1,
1)
0-
1"
0(
0!
11
1'
0/
0#
#75000
1*
01
0+
0'
1.
1#
#80000
1!
0"
0,
10
1'
0.
0)
0#
0%
0$
#85000
00
0'
1#
#90000
10
1'
0#
#95000
00
0'
1#
#100000
10
1-
1'
1(
0#
1$
#105000
1+
00
0*
0'
1/
1#
#110000
0-
1"
0(
0!
11
1'
0/
0#
#115000
01
0'
1#
#120000
1,
11
1'
1)
0#
1%
0$
#125000
1*
01
0+
0'
1.
1#
#130000
0,
1!
0)
0"
10
1'
0.
0#
#135000
00
0'
1#
#140000
10
1-
1'
1(
0#
1$
#145000
1+
00
0*
0'
1/
1#
#150000
1,
1)
0-
1"
0(
0!
11
1'
0/
0#
#155000
1*
01
0+
0'
1.
1#
#160000
1-
0,
1(
1!
0)
0"
10
1'
0.
0#
