0010000___D_Flip_Flop_Some_More_Codes/001__D_Flip_Flop_posedge/d_flip_flop.v
module d_flip_flop (
    input d,
    input clk,
    output reg q
);
    always @(posedge clk) begin
        q<=d;
    end
endmodule

0010000___D_Flip_Flop_Some_More_Codes/001__D_Flip_Flop_posedge/testbench.v
`timescale 1ns / 1ps

module d_flip_flop_tb;

    reg d;
    reg clk;
    wire q;

    d_flip_flop uut (
        .d(d),
        .clk(clk),
        .q(q)
    );

    initial begin
        clk = 0;
        forever #5 clk = ~clk;
    end

    initial begin
        $dumpfile("vcd_file.vcd");
        $dumpvars(0, uut);
        $monitor("Time: %0dns | clk = %b | d = %b | q = %b", $time, clk, d, q);
        d = 0;
        #12;

        d = 1; #10;
        d = 0; #10;
        d = 1; #10;
        d = 1; #10;
        d = 0; #10;

        #20;
        $finish;
    end

 

endmodule

0010000___D_Flip_Flop_Some_More_Codes/001__D_Flip_Flop_posedge/vcd_file.vcd
$date
	Tue Jun 24 20:02:45 2025
$end
$version
	Icarus Verilog
$end
$timescale
	1ps
$end
$scope module d_flip_flop_tb $end
$scope module uut $end
$var wire 1 ! clk $end
$var wire 1 " d $end
$var reg 1 # q $end
$upscope $end
$upscope $end
$enddefinitions $end
$comment Show the parameter values. $end
$dumpall
$end
#0
$dumpvars
x#
0"
0!
$end
#5000
0#
1!
#10000
0!
#12000
1"
#15000
1#
1!
#20000
0!
#22000
0"
#25000
0#
1!
#30000
0!
#32000
1"
#35000
1#
1!
#40000
0!
#45000
1!
#50000
0!
#52000
0"
#55000
0#
1!
