0010011__4_Bit_Synchronous_Binary_Counter/flipflop.v
module t_flip_flop (
    input wire clk,
    input wire rst,
    input wire t,
    output reg q
);

always @(posedge clk) 
    begin
        if (rst)
            q <= 1'b0;
        else
            q <= t ^ q;
    end
endmodule

0010011__4_Bit_Synchronous_Binary_Counter/4_bit_binary_counter.v
module four_bit_binary_counter(
    input t,
    input clk,
    input reset,
    output Qa,
    output Qb,
    output Qc,
    output Qd
);
wire Ta, Tb, Tc, Td;

t_flip_flop m1(
    .t(Ta),
    .clk(clk),
    .rst(reset),
    .q(Qa)
);
t_flip_flop m2(
    .t(Tb),
    .clk(clk),
    .rst(reset),
    .q(Qb)
);
t_flip_flop m3(
    .t(Tc),
    .clk(clk),
    .rst(reset),
    .q(Qc)
);
t_flip_flop m4(
    .t(Td),
    .clk(clk),
    .rst(reset),
    .q(Qd)
);

assign Ta = 1;
assign Tb = Qa;
assign Tc = Qb & Qa;
assign Td = Qc & Qb & Qa;

endmodule

0010011__4_Bit_Synchronous_Binary_Counter/testbench.v
`timescale 10ps/1ps

module four_bit_binary_counter_tb;
    reg clk, rst, t;
    wire qa, qb, qc, qd;

    four_bit_binary_counter uut(
        .clk(clk),
        .reset(rst),
        .t(t),
        .Qa(qa),
        .Qb(qb),
        .Qc(qc),
        .Qd(qd)
    );

    initial 
    begin
        clk = 0;
        forever #5 clk = ~clk;
    end

    initial
    begin
        $dumpfile("vcd_file.vcd");
        $dumpvars(0,four_bit_binary_counter_tb);

        $monitor("Time : %0t | Clk : %b | Reset : %b | T : %b | Qd Qc Qb Qa : %b %b %b %b",$time, clk, rst, t, qd, qc, qb, qa);
        rst =1 ; t = 0;
        #10 rst = 0;
        t = 1;
        #200;
        #10 $finish;
    end
endmodule

0010011__4_Bit_Synchronous_Binary_Counter/vcd_file.vcd
$date
	Tue Jun 24 19:34:59 2025
$end
$version
	Icarus Verilog
$end
$timescale
	1ps
$end
$scope module four_bit_binary_counter_tb $end
$var wire 1 ! qd $end
$var wire 1 " qc $end
$var wire 1 # qb $end
$var wire 1 $ qa $end
$var reg 1 % clk $end
$var reg 1 & rst $end
$var reg 1 ' t $end
$scope module uut $end
$var wire 1 ( Ta $end
$var wire 1 ) Tb $end
$var wire 1 * Tc $end
$var wire 1 + Td $end
$var wire 1 % clk $end
$var wire 1 & reset $end
$var wire 1 ' t $end
$var wire 1 ! Qd $end
$var wire 1 " Qc $end
$var wire 1 # Qb $end
$var wire 1 $ Qa $end
$scope module m1 $end
$var wire 1 % clk $end
$var wire 1 & rst $end
$var wire 1 ( t $end
$var reg 1 $ q $end
$upscope $end
$scope module m2 $end
$var wire 1 % clk $end
$var wire 1 & rst $end
$var wire 1 ) t $end
$var reg 1 # q $end
$upscope $end
$scope module m3 $end
$var wire 1 % clk $end
$var wire 1 & rst $end
$var wire 1 * t $end
$var reg 1 " q $end
$upscope $end
$scope module m4 $end
$var wire 1 % clk $end
$var wire 1 & rst $end
$var wire 1 + t $end
$var reg 1 ! q $end
$upscope $end
$upscope $end
$upscope $end
$enddefinitions $end
$comment Show the parameter values. $end
$dumpall
$end
#0
$dumpvars
x+
x*
x)
1(
0'
1&
0%
x$
x#
x"
x!
$end
#50
0+
0*
0)
0$
0#
0"
0!
1%
#100
0%
1'
0&
#150
1)
1$
1%
#200
0%
#250
0)
0$
1#
1%
#300
0%
#350
1*
1)
1$
1%
#400
0%
#450
0*
0)
0$
0#
1"
1%
#500
0%
#550
1)
1$
1%
#600
0%
#650
0)
0$
1#
1%
#700
0%
#750
1+
1*
1)
1$
1%
#800
0%
#850
0+
0*
0)
0$
0#
0"
1!
1%
#900
0%
#950
1)
1$
1%
#1000
0%
#1050
0)
0$
1#
1%
#1100
0%
#1150
1*
1)
1$
1%
#1200
0%
#1250
0*
0)
0$
0#
1"
1%
#1300
0%
#1350
1)
1$
1%
#1400
0%
#1450
0)
0$
1#
1%
#1500
0%
#1550
1+
1*
1)
1$
1%
#1600
0%
#1650
0+
0*
0)
0$
0#
0"
0!
1%
#1700
0%
#1750
1)
1$
1%
#1800
0%
#1850
0)
0$
1#
1%
#1900
0%
#1950
1*
1)
1$
1%
#2000
0%
#2050
0*
0)
0$
0#
1"
1%
#2100
0%
#2150
1)
1$
1%
