0010000__D_Flip_Flop_with_Asynchronus_Reset/d_flip_flop.v
module d_flip_flop_async_reset (
    input wire clk,
    input wire rst,
    input wire d,
    output reg q
);

always @(posedge clk or posedge rst) begin
    if (rst)
        q <= 1'b0;
    else
        q <= d;
end

endmodule

0010000__D_Flip_Flop_with_Asynchronus_Reset/testbench.v
module tb_d_flip_flop_async_reset;

reg clk;
reg rst;
reg d;
wire q;

d_flip_flop_async_reset uut(
    .clk(clk),
    .rst(rst),
    .d(d),
    .q(q)
);

initial begin
    clk = 0;
    forever #5 clk = ~clk;
end

initial begin
    $dumpfile("d_flip_flop.vcd");
    $dumpvars(0, tb_d_flip_flop_async_reset);
    $monitor("Time=%0t | clk=%b rst=%b d=%b q=%b", $time, clk, rst, d, q);

    rst = 1; d = 0;
    #12 rst = 0; d = 1;
    #10 d = 0;
    #10 rst = 1;
    #5 rst = 0; d = 1;
    #10 $finish;
end

endmodule

0010000__D_Flip_Flop_with_Asynchronus_Reset/d_flip_flop.vcd
$date
	Tue Jun 17 17:08:53 2025
$end
$version
	Icarus Verilog
$end
$timescale
	1s
$end
$scope module tb_d_flip_flop_async_reset $end
$var wire 1 ! q $end
$var reg 1 " clk $end
$var reg 1 # d $end
$var reg 1 $ rst $end
$scope module uut $end
$var wire 1 " clk $end
$var wire 1 # d $end
$var wire 1 $ rst $end
$var reg 1 ! q $end
$upscope $end
$upscope $end
$enddefinitions $end
$comment Show the parameter values. $end
$dumpall
$end
#0
$dumpvars
1$
0#
0"
0!
$end
#5
1"
#10
0"
#12
1#
0$
#15
1!
1"
#20
0"
#22
0#
#25
0!
1"
#30
0"
#32
1$
#35
1"
#37
1#
0$
#40
0"
#45
1!
1"
