3_4_Bit_Ripple_Carry_Adder/full_adder.v
module full_adder(
    input A,
    input B,
    input Cin,
    output sum,
    output cout
);
    assign sum = A^B^Cin;
    assign cout = A&B | Cin&(A^B);
    
endmodule

3_4_Bit_Ripple_Carry_Adder/ripple_carry_adder.v
module ripple_carry_adder(
    input [3:0] A,
    input [3:0] B,
    output [4:0] Sum
);
    wire s_0, s_1, s_2, s_3;
    wire c_0, c_1, c_2, c_3;

    //Cin will be zero at first
    full_adder first(
        .A(A[0]),
        .B(B[0]),
        .Cin(1'b0),
        .sum(s_0),
        .cout(c_0)
    );

    full_adder second(
        .A(A[1]),
        .B(B[1]),
        .Cin(c_0),
        .sum(s_1),
        .cout(c_1)
    );

    full_adder third(
        .A(A[2]),
        .B(B[2]),
        .Cin(c_1),
        .sum(s_2),
        .cout(c_2)
    );

    full_adder fourth(
        .A(A[3]),
        .B(B[3]),
        .Cin(c_2),
        .sum(s_3),
        .cout(c_3)
    );

    assign Sum = {c_3, s_3, s_2, s_1, s_0};
    
endmodule

3_4_Bit_Ripple_Carry_Adder/testbench.v
`timescale 10ns/1ns

module ripple_carry_adder_tb;
    reg [3:0] A;
    reg [3:0] B;
    wire [4:0] Sum;

    ripple_carry_adder uut(
        .A(A),
        .B(B),
        .Sum(Sum)
    );

    initial begin
        $dumpfile("ripple_carry.vcd");
        $dumpvars(0,uut);

        A = 4'b0000; 
        B = 4'b0000;
        $monitor("Time :%t | A : %b | B :%b | Sum : %b",$time,A,B,Sum);
        
        #10 A = 4'b0001; B = 4'b0000;
        #10 A = 4'b0001; B = 4'b1001;
        #10 A = 4'b0010; B = 4'b0001;
        #10 A = 4'b0010; B = 4'b0010;
        #10 A = 4'b0011; B = 4'b0010;
        #10 A = 4'b0011; B = 4'b0011;
        #10 A = 4'b0100; B = 4'b1100;
        #10 A = 4'b1001; B = 4'b1100;
        #10 A = 4'b1111; B = 4'b1000;

        #10 $finish;
    end
    
endmodule

3_4_Bit_Ripple_Carry_Adder/ripple_carry.vcd
$date
	Fri Jun 06 16:32:47 2025
$end
$version
	Icarus Verilog
$end
$timescale
	1ns
$end
$scope module ripple_carry_adder_tb $end
$scope module uut $end
$var wire 4 ! A [3:0] $end
$var wire 4 " B [3:0] $end
$var wire 1 # s_3 $end
$var wire 1 $ s_2 $end
$var wire 1 % s_1 $end
$var wire 1 & s_0 $end
$var wire 1 ' c_3 $end
$var wire 1 ( c_2 $end
$var wire 1 ) c_1 $end
$var wire 1 * c_0 $end
$var wire 5 + Sum [4:0] $end
$scope module first $end
$var wire 1 , A $end
$var wire 1 - B $end
$var wire 1 . Cin $end
$var wire 1 * cout $end
$var wire 1 & sum $end
$upscope $end
$scope module fourth $end
$var wire 1 / A $end
$var wire 1 0 B $end
$var wire 1 ' cout $end
$var wire 1 # sum $end
$var wire 1 ( Cin $end
$upscope $end
$scope module second $end
$var wire 1 1 A $end
$var wire 1 2 B $end
$var wire 1 * Cin $end
$var wire 1 ) cout $end
$var wire 1 % sum $end
$upscope $end
$scope module third $end
$var wire 1 3 A $end
$var wire 1 4 B $end
$var wire 1 ) Cin $end
$var wire 1 ( cout $end
$var wire 1 $ sum $end
$upscope $end
$upscope $end
$upscope $end
$enddefinitions $end
$comment Show the parameter values. $end
$dumpall
$end
#0
$dumpvars
04
03
02
01
00
0/
0.
0-
0,
b0 +
0*
0)
0(
0'
0&
0%
0$
0#
b0 "
b0 !
$end
#100
b1 +
1&
1,
b1 !
#200
1%
0&
1*
b1010 +
1#
1-
10
b1001 "
#300
0$
0)
0#
1&
0*
b11 +
1%
00
0,
11
b1 "
b10 !
#400
1$
0&
b100 +
0%
1)
0-
12
b10 "
#500
b101 +
1&
1,
b11 !
#600
1%
b110 +
0&
1*
1-
b11 "
#700
1'
0%
b10000 +
0$
0*
0)
1(
0-
02
14
10
0,
01
13
b1100 "
b100 !
#800
1&
1$
0(
b10101 +
0#
1,
03
1/
b1001 !
#900
b10111 +
1%
04
11
13
b1000 "
b1111 !
