0001100__4_Bit_Magnitude_Comparator/4_bit_comparator.v
// it is implemented in 7485 IC

module four_bit_comparator(
    input [3:0] A,
    input [3:0] B,
    output AGB,
    output AEB,
    output ALB
);
    //for A=B
    wire x1, x2, x3, x0;

    xnor u1(x3, A[3], B[3]);
    xnor u2(x2, A[2], B[2]);
    xnor u3(x1, A[1], B[1]);
    xnor u4(x0, A[0], B[0]);
    and u5(AEB, x1, x2, x3, x0);

    
    //for A>B
    wire og1, og2, og3, og4;
    wire yg0 ,yg1, yg2;
    wire notb3, notb2, notb1, notb0;

    not u6(notb3, B[3]);
    not u7(notb2, B[2]);
    not u8(notb1, B[1]);
    not u9(notb0, B[0]);

    and u10(og1, A[3], notb3);
    and u11(yg2, A[2], notb2);
    and u12(yg1, A[1], notb1);
    and u13(yg0, A[0], notb0);

    and u14(og2, x3, yg2);
    and u15(og3, x3, x2, yg1);
    and u16(og4, x3, x2, x1, yg0);

    or u17(AGB, og1, og2, og3, og4);

    //for A<B
    wire ol1, ol2, ol3, ol4;
    wire yl0 ,yl1, yl2;
    wire nota3, nota2, nota1, nota0;

    not u18(nota3, A[3]);
    not u19(nota2, A[2]);
    not u20(nota1, A[1]);
    not u21(nota0, A[0]);

    and u22(ol1, B[3], nota3);
    and u23(yl2, B[2], nota2);
    and u24(yl1, B[1], nota1);
    and u25(yl0, B[0], nota0);

    and u26(ol2, x3, yl2);
    and u27(ol3, x3, x2, yl1);
    and u28(ol4, x3, x2, x1, yl0);

    or u29(ALB, ol1, ol2, ol3, ol4);
    
endmodule

0001100__4_Bit_Magnitude_Comparator/testbench.v
module four_bit_comparator_tb;

    reg [3:0] A;
    reg [3:0] B;

    wire AGB, AEB, ALB;

    four_bit_comparator uut(
        .A(A),
        .B(B),
        .AGB(AGB),
        .AEB(AEB),
        .ALB(ALB)
    );

    initial begin
        $dumpfile("vcd_comparator.vcd");
        $dumpvars(0,uut);

        $monitor("Time : %0t | A : %b | B : %b | AGB : %b | AEB : %b | ALB : %b", $time, A, B, AGB, AEB, ALB);
        A = 4'b0000; B = 4'b0000;
        #10 A = 4'b1100; B = 4'b0110;
        #10 A = 4'b1110; B = 4'b1110;
        #10 A = 4'b0011; B = 4'b0111;
        #10 A = 4'b0010; B = 4'b0011;
        #10 A = 4'b1110; B = 4'b1110;
        #10 A = 4'b1111; B = 4'b1110;
        #10 A = 4'b0110; B = 4'b0010;
        #10 A = 4'b0010; B = 4'b0110;
        #10 $finish;
    end


endmodule

0001100__4_Bit_Magnitude_Comparator/vcd_comparator.vcd
$date
	Fri Jun 13 13:20:36 2025
$end
$version
	Icarus Verilog
$end
$timescale
	1s
$end
$scope module four_bit_comparator_tb $end
$scope module uut $end
$var wire 4 ! A [3:0] $end
$var wire 1 " AEB $end
$var wire 1 # AGB $end
$var wire 1 $ ALB $end
$var wire 4 % B [3:0] $end
$var wire 1 & nota0 $end
$var wire 1 ' nota1 $end
$var wire 1 ( nota2 $end
$var wire 1 ) nota3 $end
$var wire 1 * notb0 $end
$var wire 1 + notb1 $end
$var wire 1 , notb2 $end
$var wire 1 - notb3 $end
$var wire 1 . og1 $end
$var wire 1 / og2 $end
$var wire 1 0 og3 $end
$var wire 1 1 og4 $end
$var wire 1 2 ol1 $end
$var wire 1 3 ol2 $end
$var wire 1 4 ol3 $end
$var wire 1 5 ol4 $end
$var wire 1 6 x0 $end
$var wire 1 7 x1 $end
$var wire 1 8 x2 $end
$var wire 1 9 x3 $end
$var wire 1 : yg0 $end
$var wire 1 ; yg1 $end
$var wire 1 < yg2 $end
$var wire 1 = yl0 $end
$var wire 1 > yl1 $end
$var wire 1 ? yl2 $end
$upscope $end
$upscope $end
$enddefinitions $end
$comment Show the parameter values. $end
$dumpall
$end
#0
$dumpvars
0?
0>
0=
0<
0;
0:
19
18
17
16
05
04
03
02
01
00
0/
0.
1-
1,
1+
1*
1)
1(
1'
1&
b0 %
0$
0#
1"
b0 !
$end
#10
0"
1#
07
0,
0+
1>
09
1.
0<
0)
0(
b110 %
b1100 !
#20
0#
0.
1"
0>
19
0-
17
0'
b1110 %
b1110 !
#30
1$
13
0"
1?
1-
0*
08
0:
1)
1(
0&
b111 %
b11 !
#40
15
03
1=
18
1,
0?
06
1&
b11 %
b10 !
#50
0$
1"
05
0#
0/
16
0-
0,
1*
0=
0.
0<
0)
0(
b1110 %
b1110 !
#60
1#
0"
11
06
1:
0&
b1111 !
#70
1/
1#
1<
01
08
1-
1,
16
0:
1)
1&
b10 %
b110 !
#80
1$
0#
13
0/
0,
1?
0<
1(
b110 %
b10 !
