0011010__Johnson_Counter/d_flipflop.v
module d_flipflop(
    input d,
    input clear,
    input ori,
    input clk,
    output reg q,
    output q_bar
);
    assign q_bar =~q;
    always @(posedge clk or posedge clear) begin
        if (ori & clear)
            q <= 1'b0;
        else
            q <= d;
    end
endmodule

0011010__Johnson_Counter/johnson_counter.v
module johnson_counter(
    input clk,
    input clear,
    input ori,
    output [3:0] q_out
);
    wire [3:0] D;
    wire [3:0] Q;
    wire [3:0] Q_bar;

    assign D[0] = Q_bar[3];
    assign D[1] = Q[0];
    assign D[2] = Q[1];
    assign D[3] = Q[2];

    assign q_out = Q;
    d_flipflop m1(
        .d(D[0]),
        .clear(clear),
        .ori(ori),
        .clk(clk),
        .q(Q[0]),
        .q_bar(Q_bar[0])
    );

    d_flipflop m2(
        .d(D[1]),
        .clear(clear),
        .ori(ori),
        .clk(clk),
        .q(Q[1]),
        .q_bar(Q_bar[1])
    );

    d_flipflop m3(
        .d(D[2]),
        .clear(clear),
        .ori(ori),
        .clk(clk),
        .q(Q[2]),
        .q_bar(Q_bar[2])
    );

    d_flipflop m4(
        .d(D[3]),
        .clear(clear),
        .ori(ori),
        .clk(clk),
        .q(Q[3]),
        .q_bar(Q_bar[3])
    );

    

endmodule

0011010__Johnson_Counter/johnson_counter_tb.v
`timescale 1ns/1ps

module johnson_counter_tb;

    reg clk;
    reg clear;
    reg ori;
    wire [3:0] q_out;

    johnson_counter uut (
        .clk(clk),
        .clear(clear),
        .ori(ori),
        .q_out(q_out)
    );

    initial begin
        clk = 0;
        forever #5 clk = ~clk;
    end

    initial begin
        $dumpfile("vcd_file.vcd");
        $dumpvars(0, johnson_counter_tb);
        $monitor("Time=%0t clk=%b clear=%b ori=%b q_out=%b", 
                 $time, clk, clear, ori, q_out);

        clear = 1;ori = 1;
        #40;

        clear = 0; ori = 1;
        #5;

        #100;

        $finish;
    end

endmodule

0011010__Johnson_Counter/vcd_file.vcd
$date
	Fri Jun 27 15:33:33 2025
$end
$version
	Icarus Verilog
$end
$timescale
	1ps
$end
$scope module johnson_counter_tb $end
$var wire 4 ! q_out [3:0] $end
$var reg 1 " clear $end
$var reg 1 # clk $end
$var reg 1 $ ori $end
$scope module uut $end
$var wire 1 " clear $end
$var wire 1 # clk $end
$var wire 1 $ ori $end
$var wire 4 % q_out [3:0] $end
$var wire 4 & Q_bar [3:0] $end
$var wire 4 ' Q [3:0] $end
$var wire 4 ( D [3:0] $end
$scope module m1 $end
$var wire 1 " clear $end
$var wire 1 # clk $end
$var wire 1 ) d $end
$var wire 1 $ ori $end
$var wire 1 * q_bar $end
$var reg 1 + q $end
$upscope $end
$scope module m2 $end
$var wire 1 " clear $end
$var wire 1 # clk $end
$var wire 1 , d $end
$var wire 1 $ ori $end
$var wire 1 - q_bar $end
$var reg 1 . q $end
$upscope $end
$scope module m3 $end
$var wire 1 " clear $end
$var wire 1 # clk $end
$var wire 1 / d $end
$var wire 1 $ ori $end
$var wire 1 0 q_bar $end
$var reg 1 1 q $end
$upscope $end
$scope module m4 $end
$var wire 1 " clear $end
$var wire 1 # clk $end
$var wire 1 2 d $end
$var wire 1 $ ori $end
$var wire 1 3 q_bar $end
$var reg 1 4 q $end
$upscope $end
$upscope $end
$upscope $end
$enddefinitions $end
$comment Show the parameter values. $end
$dumpall
$end
#0
$dumpvars
04
13
02
01
10
0/
0.
1-
0,
0+
1*
1)
b1 (
b0 '
b1111 &
b0 %
1$
0#
1"
b0 !
$end
#5000
1#
#10000
0#
#15000
1#
#20000
0#
#25000
1#
#30000
0#
#35000
1#
#40000
0#
0"
#45000
1,
b1110 &
0*
b11 (
b1 !
b1 %
b1 '
1+
1#
#50000
0#
#55000
1/
b1100 &
0-
b111 (
b11 !
b11 %
b11 '
1.
1#
#60000
0#
#65000
12
b1000 &
00
b1111 (
b111 !
b111 %
b111 '
11
1#
#70000
0#
#75000
0)
b1110 (
b0 &
03
b1111 !
b1111 %
b1111 '
14
1#
#80000
0#
#85000
0,
b1 &
1*
b1100 (
b1110 !
b1110 %
b1110 '
0+
1#
#90000
0#
#95000
0/
b11 &
1-
b1000 (
b1100 !
b1100 %
b1100 '
0.
1#
#100000
0#
#105000
02
b111 &
10
b0 (
b1000 !
b1000 %
b1000 '
01
1#
#110000
0#
#115000
1)
b1 (
b1111 &
13
b0 !
b0 %
b0 '
04
1#
#120000
0#
#125000
1,
b1110 &
0*
b11 (
b1 !
b1 %
b1 '
1+
1#
#130000
0#
#135000
1/
b1100 &
0-
b111 (
b11 !
b11 %
b11 '
1.
1#
#140000
0#
#145000
12
b1000 &
00
b1111 (
b111 !
b111 %
b111 '
11
1#
