0011001__Ring_Counter/d_flipflop.v
module d_flipflop(
    input d,
    input preset,
    input clear,
    input ori,
    input clk,
    output reg q
);
    always @(posedge clk or posedge preset or posedge clear) begin
        if (ori & preset)
            q <= 1'b1;
        else if (ori & clear)
            q <= 1'b0;
        else
            q <= d;
    end
endmodule

0011001__Ring_Counter/ring_counter.v
module ring_counter(
    input clk,
    input preset,
    input clear,
    input ori,
    output [3:0] q_out
);
    wire [3:0] D;
    wire [3:0] Q;

    assign D[0] = Q[3];
    assign D[1] = Q[0];
    assign D[2] = Q[1];
    assign D[3] = Q[2];

    assign q_out = Q;
    d_flipflop m1(
        .d(D[0]),
        .preset(preset),
        .clear(clear),
        .ori(ori),
        .clk(clk),
        .q(Q[0])
    );

    d_flipflop m2(
        .d(D[1]),
        .preset(1'b0),
        .clear(clear),
        .ori(ori),
        .clk(clk),
        .q(Q[1])
    );

    d_flipflop m3(
        .d(D[2]),
        .preset(1'b0),
        .clear(clear),
        .ori(ori),
        .clk(clk),
        .q(Q[2])
    );

    d_flipflop m4(
        .d(D[3]),
        .preset(1'b0),
        .clear(clear),
        .ori(ori),
        .clk(clk),
        .q(Q[3])
    );

    

endmodule

0011001__Ring_Counter/ring_counter_tb.v
`timescale 1ns/1ps

module ring_counter_tb;

    reg clk;
    reg preset;
    reg clear;
    reg ori;
    wire [3:0] q_out;

    ring_counter uut (
        .clk(clk),
        .preset(preset),
        .clear(clear),
        .ori(ori),
        .q_out(q_out)
    );

    initial begin
        clk = 0;
        forever #5 clk = ~clk;
    end

    initial begin
        $dumpfile("vcd_file.vcd");
        $dumpvars(0, ring_counter_tb);
        $monitor("Time=%0t clk=%b preset=%b clear=%b ori=%b q_out=%b", 
                 $time, clk, preset, clear, ori, q_out);

        clear = 1; preset = 0; ori = 1;
        #40;

        clear = 0; preset = 1; ori = 1;
        #5;

        preset = 0;
        #100;

        $finish;
    end

endmodule

0011001__Ring_Counter/vcd_file.vcd
$date
	Fri Jun 27 14:51:12 2025
$end
$version
	Icarus Verilog
$end
$timescale
	1ps
$end
$scope module ring_counter_tb $end
$var wire 4 ! q_out [3:0] $end
$var reg 1 " clear $end
$var reg 1 # clk $end
$var reg 1 $ ori $end
$var reg 1 % preset $end
$scope module uut $end
$var wire 1 " clear $end
$var wire 1 # clk $end
$var wire 1 $ ori $end
$var wire 1 % preset $end
$var wire 4 & q_out [3:0] $end
$var wire 4 ' Q [3:0] $end
$var wire 4 ( D [3:0] $end
$scope module m1 $end
$var wire 1 " clear $end
$var wire 1 # clk $end
$var wire 1 ) d $end
$var wire 1 $ ori $end
$var wire 1 % preset $end
$var reg 1 * q $end
$upscope $end
$scope module m2 $end
$var wire 1 " clear $end
$var wire 1 # clk $end
$var wire 1 + d $end
$var wire 1 $ ori $end
$var wire 1 , preset $end
$var reg 1 - q $end
$upscope $end
$scope module m3 $end
$var wire 1 " clear $end
$var wire 1 # clk $end
$var wire 1 . d $end
$var wire 1 $ ori $end
$var wire 1 / preset $end
$var reg 1 0 q $end
$upscope $end
$scope module m4 $end
$var wire 1 " clear $end
$var wire 1 # clk $end
$var wire 1 1 d $end
$var wire 1 $ ori $end
$var wire 1 2 preset $end
$var reg 1 3 q $end
$upscope $end
$upscope $end
$upscope $end
$enddefinitions $end
$comment Show the parameter values. $end
$dumpall
$end
#0
$dumpvars
03
02
01
00
0/
0.
0-
0,
0+
0*
0)
b0 (
b0 '
b0 &
0%
1$
0#
1"
b0 !
$end
#5000
1#
#10000
0#
#15000
1#
#20000
0#
#25000
1#
#30000
0#
#35000
1#
#40000
1+
b10 (
b1 !
b1 &
b1 '
1*
0#
1%
0"
#45000
0+
1.
b100 (
0*
b10 !
b10 &
b10 '
1-
1#
0%
#50000
0#
#55000
0.
11
b1000 (
0-
b100 !
b100 &
b100 '
10
1#
#60000
0#
#65000
01
1)
b1 (
00
b1000 !
b1000 &
b1000 '
13
1#
#70000
0#
#75000
1+
0)
b10 (
1*
b1 !
b1 &
b1 '
03
1#
#80000
0#
#85000
0+
1.
b100 (
0*
b10 !
b10 &
b10 '
1-
1#
#90000
0#
#95000
0.
11
b1000 (
0-
b100 !
b100 &
b100 '
10
1#
#100000
0#
#105000
01
1)
b1 (
00
b1000 !
b1000 &
b1000 '
13
1#
#110000
0#
#115000
1+
0)
b10 (
1*
b1 !
b1 &
b1 '
03
1#
#120000
0#
#125000
0+
1.
b100 (
0*
b10 !
b10 &
b10 '
1-
1#
#130000
0#
#135000
0.
11
b1000 (
0-
b100 !
b100 &
b100 '
10
1#
#140000
0#
#145000
01
1)
b1 (
00
b1000 !
b1000 &
b1000 '
13
1#
