0011000__Shift_Register_Parallel_In_Serial_Out/d_flipflop.v
module d_flipflop(
    input d,
    input clk,
    input rst,
    output reg q
);
    always @(posedge clk, posedge rst) begin
        if(rst) q<=1'b0;
        
        else q<=d;
    end
    
endmodule

0011000__Shift_Register_Parallel_In_Serial_Out/shift_register_PISO.v
module shift_register_PISO(
    input [3:0] data,
    input clk,
    input shift,
    input rst,
    output q_out
);
    wire load;
    assign load = ~shift;
    wire [3:0] B;
    wire [3:0] Q;  
    assign B = data;
    wire [3:0] D;

    
    assign D[0]= B[0];
    assign D[1] = (Q[0]&shift)|(B[1]&load);
    assign D[2] = (Q[1]&shift)|(B[2]&load);
    assign D[3] = (Q[2]&shift)|(B[3]&load);

    assign q_out = Q[3];
    d_flipflop m1(
        .d(D[0]),
        .clk(clk),
        .rst(rst),
        .q(Q[0])
    );
    d_flipflop m2(
        .d(D[1]),
        .clk(clk),
        .rst(rst),
        .q(Q[1])
    );
    d_flipflop m3(
        .d(D[2]),
        .clk(clk),
        .rst(rst),
        .q(Q[2])
    );
    d_flipflop m4(
        .d(D[3]),
        .clk(clk),
        .rst(rst),
        .q(Q[3])
    );
    
endmodule

0011000__Shift_Register_Parallel_In_Serial_Out/shift_register_PISO_tb.v
`timescale 1ns/1ps

module shift_register_PISO_tb;

    reg [3:0] data;
    reg clk;
    reg shift;
    reg rst;
    wire q_out;

    shift_register_PISO uut (
        .data(data),
        .clk(clk),
        .shift(shift),
        .rst(rst),
        .q_out(q_out)
    );

    always #5 clk = ~clk;

    initial begin
        $dumpfile("vcd_file.vcd");
        $dumpvars(0, shift_register_PISO_tb);
        $monitor("Time=%0t | rst=%b | shift=%b | data=%b | q_out=%b", $time, rst, shift, data, q_out);

        clk = 0;
        rst = 1;
        shift = 0;
        data = 4'b0000;

        #10 rst = 0;
        #10 data = 4'b0101; shift = 0;
        #10 shift = 1;
        #40;
        #10 shift = 0; data = 4'b1010;
        #10 shift = 1;
        #40;

        $finish;
    end

endmodule

0011000__Shift_Register_Parallel_In_Serial_Out/vcd_file.vcd
$date
	Fri Jun 27 13:23:05 2025
$end
$version
	Icarus Verilog
$end
$timescale
	1ps
$end
$scope module shift_register_PISO_tb $end
$var wire 1 ! q_out $end
$var reg 1 " clk $end
$var reg 4 # data [3:0] $end
$var reg 1 $ rst $end
$var reg 1 % shift $end
$scope module uut $end
$var wire 4 & B [3:0] $end
$var wire 1 " clk $end
$var wire 4 ' data [3:0] $end
$var wire 1 ( load $end
$var wire 1 $ rst $end
$var wire 1 % shift $end
$var wire 1 ! q_out $end
$var wire 4 ) Q [3:0] $end
$var wire 4 * D [3:0] $end
$scope module m1 $end
$var wire 1 " clk $end
$var wire 1 + d $end
$var wire 1 $ rst $end
$var reg 1 , q $end
$upscope $end
$scope module m2 $end
$var wire 1 " clk $end
$var wire 1 - d $end
$var wire 1 $ rst $end
$var reg 1 . q $end
$upscope $end
$scope module m3 $end
$var wire 1 " clk $end
$var wire 1 / d $end
$var wire 1 $ rst $end
$var reg 1 0 q $end
$upscope $end
$scope module m4 $end
$var wire 1 " clk $end
$var wire 1 1 d $end
$var wire 1 $ rst $end
$var reg 1 2 q $end
$upscope $end
$upscope $end
$upscope $end
$enddefinitions $end
$comment Show the parameter values. $end
$dumpall
$end
#0
$dumpvars
02
01
00
0/
0.
0-
0,
0+
b0 *
b0 )
1(
b0 '
b0 &
0%
1$
b0 #
0"
0!
$end
#5000
1"
#10000
0"
0$
#15000
1"
#20000
1/
1+
b101 *
0"
b101 &
b101 #
b101 '
#25000
10
b101 )
1,
1"
#30000
0/
1-
11
b1011 *
0(
0"
1%
#35000
1/
01
b111 *
1!
1.
00
b1011 )
12
1"
#40000
0"
#45000
11
b1111 *
0!
02
b111 )
10
1"
#50000
0"
#55000
1!
b1111 )
12
1"
#60000
0"
#65000
1"
#70000
0"
#75000
1"
#80000
1-
0/
11
0+
b1010 *
1(
0"
b1010 &
b1010 #
b1010 '
0%
#85000
00
b1010 )
0,
1"
#90000
0-
01
1/
b100 *
0(
0"
1%
#95000
0/
11
b1000 *
0!
0.
10
b100 )
02
1"
#100000
0"
#105000
01
b0 *
1!
12
b1000 )
00
1"
#110000
0"
#115000
0!
b0 )
02
1"
