0000010__One_Bit_Full_Adder_using_Half_Adder/half_adder.v
// This module implements a one-bit half adder

module one_bit_half_adder (
    input A,
    input B,
    output s,
    output c
);

    assign s = A ^ B;
    assign c = A & B;

endmodule

2_One_Bit_Full_Adder_using_Half_Adder/full_adder.v
module full_adder_using_half_adder(
    input A,
    input B,
    input Cin,
    output sum,
    output cout
);

wire temp_sum;
wire temp_carry;

one_bit_half_adder test(
    .A(A),
    .B(B),
    .s(temp_sum),
    .c(temp_carry)
);

wire temp_carry_second;

one_bit_half_adder test_second(
    .A(temp_sum),
    .B(Cin),
    .s(sum),
    .c(temp_carry_second)
);

assign cout = temp_carry | temp_carry_second ;

    
endmodule

2_One_Bit_Full_Adder_using_Half_Adder/full_adder_tb.v
`timescale 10ns/1ps  

module full_adder_using_half_adder_tb;

    reg a, b, cin;
    wire sum, cout;

    full_adder_using_half_adder uut(
        .A(a),
        .B(b),
        .Cin(cin),
        .sum(sum),
        .cout(cout)
    );

    initial begin
        $dumpfile("full_adder.vcd");
        $dumpvars(0, uut);

        $monitor("Time :%t  A :%b  B :%b  Cin :%b  | Sum :%b  | Cout :%b ",
                  $time, a, b, cin, sum, cout);

        a = 0; b = 0; cin = 0;
        #10 a = 0; b = 1; cin = 0;
        #10 a = 1; b = 0; cin = 0;
        #10 a = 1; b = 1; cin = 0;
        #10 a = 0; b = 0; cin = 1;
        #10 a = 0; b = 1; cin = 1;
        #10 a = 1; b = 0; cin = 1;
        #10 a = 1; b = 1; cin = 1;
        #10 $finish;
    end
    
endmodule

2_One_Bit_Full_Adder_using_Half_Adder/full_adder.vcd
$date
	Fri Jun 06 15:05:16 2025
$end
$version
	Icarus Verilog
$end
$timescale
	1ps
$end
$scope module full_adder_using_half_adder_tb $end
$scope module uut $end
$var wire 1 ! A $end
$var wire 1 " B $end
$var wire 1 # Cin $end
$var wire 1 $ cout $end
$var wire 1 % temp_sum $end
$var wire 1 & temp_carry_second $end
$var wire 1 ' temp_carry $end
$var wire 1 ( sum $end
$scope module test $end
$var wire 1 ! A $end
$var wire 1 " B $end
$var wire 1 ' c $end
$var wire 1 % s $end
$upscope $end
$scope module test_second $end
$var wire 1 % A $end
$var wire 1 # B $end
$var wire 1 & c $end
$var wire 1 ( s $end
$upscope $end
$upscope $end
$upscope $end
$enddefinitions $end
$comment Show the parameter values. $end
$dumpall
$end
#0
$dumpvars
0(
0'
0&
0%
0$
0#
0"
0!
$end
#100000
1(
1%
1"
#200000
0"
1!
#300000
0(
1$
0%
1'
1"
#400000
0$
1(
0'
1#
0"
0!
#500000
1$
0(
1&
1%
1"
#600000
0"
1!
#700000
1(
0&
0%
1'
1"
