4_4_Bit_Subtractor_using_2s_Complement/subtractor.v
// For 2s complement, add 1 in 1s complement, and for 1's complement, take negation of the input
// We know that for subtacting in 2s complement form, the number can be signed or unsigned..
// So let's there be a 5 bit number in which the msb will show the sign

//In this program the input will be in 2's complement form and we know that 2's complement of +ve number is negative and vice versa

//We also know that as its a 5 bit number, the results will go invalid if the subtractions results exceeds 15 or it's below -16.
//In 2s complement subtraction, A-B is effectively A + 2's complement of B

module four_bit_subtractor(
    input [3:0] A,
    input [3:0] B,
    output [4:0] result
);
    wire [4:0] A_0, B_0;
    assign A_0 = {1'b0, A}; 

    assign B_0 = {1'b0, ~B} + 5'b00001;
    assign result = A_0 + B_0;
endmodule

4_4_Bit_Subtractor_using_2s_Complement/subtractor_tb.v
`timescale 10ns/1ns

module subtractor_tb;
    reg [3:0] A;
    reg [3:0] B;

    wire [4:0] res;

    four_bit_subtractor uut(
        .A(A),
        .B(B),
        .result(res)
    );

    initial begin
        $dumpfile("subtractor.vcd");
        $dumpvars(0,uut);

        A = 4'b0000;
        B = 4'b0000;

        $monitor("Time :%t | A :%b | B :%b | Result :%b  ",$time, A, B, res);

        #10 A = 4'b0001; B = 4'b0000;
        #10 A = 4'b0001; B = 4'b1001;
        #10 A = 4'b0010; B = 4'b0001;
        #10 A = 4'b0010; B = 4'b0010;
        #10 A = 4'b0011; B = 4'b0010;
        #10 A = 4'b0011; B = 4'b0011;
        #10 A = 4'b0100; B = 4'b1100;
        #10 A = 4'b1001; B = 4'b1100;
        #10 A = 4'b1111; B = 4'b1000;

        #10 $finish;
    end

    
endmodule

0000100__4_Bit_Subtractor_using_2s_Complement/subtractor.vcd
$date
	Wed Jun 11 16:47:39 2025
$end
$version
	Icarus Verilog
$end
$timescale
	1ns
$end
$scope module subtractor_tb $end
$scope module uut $end
$var wire 4 ! A [3:0] $end
$var wire 4 " B [3:0] $end
$var wire 5 # result [4:0] $end
$var wire 5 $ B_0 [4:0] $end
$var wire 5 % A_0 [4:0] $end
$upscope $end
$upscope $end
$enddefinitions $end
$comment Show the parameter values. $end
$dumpall
$end
#0
$dumpvars
b0 %
b10000 $
b10000 #
b0 "
b0 !
$end
#100
b10001 #
b1 %
b1 !
#200
b1000 #
b111 $
b1001 "
#300
b1111 $
b1 "
b10001 #
b10 %
b10 !
#400
b10000 #
b1110 $
b10 "
#500
b10001 #
b11 %
b11 !
#600
b10000 #
b1101 $
b11 "
#700
b100 $
b1100 "
b1000 #
b100 %
b100 !
#800
b1101 #
b1001 %
b1001 !
#900
b1000 $
b1000 "
b10111 #
b1111 %
b1111 !
