0001111__Gray_Code_to_Binary_Converter/g_to_b_converter.v
module graycode_to_binary_converter(
    input [3:0] graycode,
    output [3:0] binary
);
    assign binary[3] = graycode[3];
    assign binary[2] = binary[3] + graycode[2];
    assign binary[1] = binary[2] + graycode[1];
    assign binary[0] = binary[1] + graycode[0];
endmodule

0001111__Gray_Code_to_Binary_Converter/testbench.v
`timescale 10ns/1ns

module graycode_to_binary_converter_tb;

    reg [3:0] gray;
    wire [3:0] bin;

    graycode_to_binary_converter uut(
        .binary(bin),
        .graycode(gray)
    );

    initial begin
        $dumpfile("vcd_gg.vcd");
        $dumpvars(0,uut);

        $monitor("Time : %0t | Graycode : %b| Binary : %b ",$time, gray, bin);

        gray = 4'b0000;
        #10 gray = 4'b0001;
        #10 gray = 4'b0010;
        #10 gray = 4'b0011;
        #10 gray = 4'b0100;
        #10 gray = 4'b0101;
        #10 gray = 4'b0111;
        #10 gray = 4'b1000;
        #10 gray = 4'b1001;
        #10 gray = 4'b1010;
        #10 gray = 4'b1011;
        #10 gray = 4'b1100;
        #10 gray = 4'b1110;
        #10 gray = 4'b1111;
        #10 $finish;
    end
endmodule

0001111__Gray_Code_to_Binary_Converter/vcd_gg.vcd
$date
	Sat Jun 14 13:32:14 2025
$end
$version
	Icarus Verilog
$end
$timescale
	1ns
$end
$scope module graycode_to_binary_converter_tb $end
$scope module uut $end
$var wire 4 ! graycode [3:0] $end
$var wire 4 " binary [3:0] $end
$upscope $end
$upscope $end
$enddefinitions $end
$comment Show the parameter values. $end
$dumpall
$end
#0
$dumpvars
b0 "
b0 !
$end
#100
b1 "
b1 !
#200
b11 "
b10 !
#300
b10 "
b11 !
#400
b111 "
b100 !
#500
b110 "
b101 !
#600
b101 "
b111 !
#700
b1111 "
b1000 !
#800
b1110 "
b1001 !
#900
b1100 "
b1010 !
#1000
b1101 "
b1011 !
#1100
b1000 "
b1100 !
#1200
b1011 "
b1110 !
#1300
b1010 "
b1111 !
