0000110__4_to_1_MUX_using_Behavioural_Verilog/4_to_1_MUX.v
//We have to design a 4 to 1 multiplexer using behavioural verilog
//we can directly take the 4 bit input stream in which each bits will be I0, I1, I2, and I3
//As 4 input are there then there would be 2 bit select stream
module four_to_one_mux(
    input [3:0] in,
    input [1:0] sel,
    output out
);
    assign out = in[sel];
endmodule

0000110__4_to_1_MUX_using_Behavioural_Verilog/testbench.v
`timescale 10ns/1ns

module four_to_one_mux_tb;
    reg [3:0] in;
    reg [1:0] sel;
    
    wire out;

    four_to_one_mux uut(
        .in(in),
        .sel(sel),
        .out(out)
    );

    initial begin
        $dumpfile("vcd_4_to_1_mux.vcd");
        $dumpvars(0,uut);

        $monitor("Time :%0t | 4-Bit Input : %b | 2-Bit Select : %b | Output : %b ",$time,in,sel,out);
        in = 4'b0000;
        sel = 2'b00;

        #10 in = 4'b1010 ; sel = 2'b01;
        #10 in = 4'b1110 ; sel = 2'b00;
        #10 in = 4'b1011 ; sel = 2'b10;
        #10 in = 4'b0010 ; sel = 2'b11;
        #10 in = 4'b0011 ; sel = 2'b01;
        #10 in = 4'b1111 ; sel = 2'b00;
        #10 in = 4'b0111 ; sel = 2'b11;
        #10 in = 4'b1000 ; sel = 2'b10;
        #10 in = 4'b1001 ; sel = 2'b00;

        #10 $finish;
    end

endmodule

0000110__4_to_1_MUX_using_Behavioural_Verilog/vcd_4_to_1_mux.vcd
$date
	Wed Jun 11 18:32:47 2025
$end
$version
	Icarus Verilog
$end
$timescale
	1ns
$end
$scope module four_to_one_mux_tb $end
$scope module uut $end
$var wire 4 ! in [3:0] $end
$var wire 2 " sel [1:0] $end
$var wire 1 # out $end
$upscope $end
$upscope $end
$enddefinitions $end
$comment Show the parameter values. $end
$dumpall
$end
#0
$dumpvars
0#
b0 "
b0 !
$end
#100
1#
b1 "
b1010 !
#200
0#
b0 "
b1110 !
#300
b10 "
0#
b1011 !
#400
b11 "
b10 !
#500
1#
b1 "
b11 !
#600
b0 "
b1111 !
#700
0#
b11 "
b111 !
#800
b10 "
0#
b1000 !
#900
1#
b0 "
b1001 !
