0000111__8_to_1_MUX_using_Hierarchical_Module/2_to_1_MUX.v
module two_to_one_mux(
    input [1:0]I,
    input S,
    output Y
);
    wire nots, and_1, and_2;

    not u1(nots, S);
    and u2(and_1, I[0], nots);
    and u3(and_2, I[1], S);
    or u4(Y, and_1, and_2);
    
endmodule

0000111__8_to_1_MUX_using_Hierarchical_Module/4_to_1_MUX.v
module four_to_one_mux(
    input [3:0] In,
    input[1:0] Se,
    output R
);
    wire [1:0] t;
    two_to_one_mux M1(
        .I(In[1:0]),
        .S(Se[0]),
        .Y(t[0])
    );

    two_to_one_mux M2(
        .I(In[3:2]),
        .S(Se[0]),
        .Y(t[1])
    );

    two_to_one_mux M3(
        .I(t[1:0]),
        .S(Se[1]),
        .Y(R)
    );
    
endmodule

0000111__8_to_1_MUX_using_Hierarchical_Module/8_to_1_MUX.v
module eight_to_one_mux(
    input [7:0] in,
    input [2:0] sel,
    output out
);
    wire [1:0] t;

    four_to_one_mux F1(
        .In(in[3:0]),
        .Se(sel[1:0]),
        .R(t[0])
    );

    four_to_one_mux F2(
        .In(in[7:4]),
        .Se(sel[1:0]),
        .R(t[1])
    );

    two_to_one_mux M0(
        .I(t[1:0]),
        .S(sel[2]),
        .Y(out)
    );
    
endmodule

//iverilog -o file.vvp 2_to_1_MUX.v 4_to_1_MUX.v 8_to_1_MUX.v 8_to_1_tb.v

0000111__8_to_1_MUX_using_Hierarchical_Module/8_to_1_tb.v
`timescale 10ns/1ns

module eight_to_one_mux_tb;

    reg [7:0] inp;
    reg [2:0] select;

    wire out;

    eight_to_one_mux uut(
        .in(inp),
        .sel(select),
        .out(out)
    );

    initial 
    begin
        $dumpfile("8_to_1_VCD.vcd");
        $dumpvars(0,uut);

        $monitor("Time : %0t | 8-Bit Input : %b | 3-Bit Select : %b | Output : %b",$time, inp, select, out);
        inp = 8'b00000000;
        select = 3'b000;

        #5 inp = 8'b01010011; select = 3'b001;
        #5 inp = 8'b01010011; select = 3'b010;
        #5 inp = 8'b01011011; select = 3'b011;
        #5 inp = 8'b11010011; select = 3'b110;
        #5 inp = 8'b01010011; select = 3'b111;
        #5 inp = 8'b01010011; select = 3'b100;
        #5 inp = 8'b11010011; select = 3'b101;
        #5 inp = 8'b01110011; select = 3'b110;
        #5 inp = 8'b01000011; select = 3'b111;
        #5 inp = 8'b10010011; select = 3'b001;
        #5 inp = 8'b11000010; select = 3'b011;
        #5 $finish;
    end

endmodule

0000111__8_to_1_MUX_using_Hierarchical_Module/8_to_1_VCD.vcd
$date
	Thu Jun 12 12:13:47 2025
$end
$version
	Icarus Verilog
$end
$timescale
	1ns
$end
$scope module eight_to_one_mux_tb $end
$scope module uut $end
$var wire 8 ! in [7:0] $end
$var wire 3 " sel [2:0] $end
$var wire 2 # t [1:0] $end
$var wire 1 $ out $end
$scope module F1 $end
$var wire 4 % In [3:0] $end
$var wire 2 & Se [1:0] $end
$var wire 2 ' t [1:0] $end
$var wire 1 ( R $end
$scope module M1 $end
$var wire 2 ) I [1:0] $end
$var wire 1 * S $end
$var wire 1 + Y $end
$var wire 1 , and_1 $end
$var wire 1 - and_2 $end
$var wire 1 . nots $end
$upscope $end
$scope module M2 $end
$var wire 2 / I [1:0] $end
$var wire 1 0 S $end
$var wire 1 1 Y $end
$var wire 1 2 and_1 $end
$var wire 1 3 and_2 $end
$var wire 1 4 nots $end
$upscope $end
$scope module M3 $end
$var wire 2 5 I [1:0] $end
$var wire 1 6 S $end
$var wire 1 ( Y $end
$var wire 1 7 and_1 $end
$var wire 1 8 and_2 $end
$var wire 1 9 nots $end
$upscope $end
$upscope $end
$scope module F2 $end
$var wire 4 : In [3:0] $end
$var wire 2 ; Se [1:0] $end
$var wire 2 < t [1:0] $end
$var wire 1 = R $end
$scope module M1 $end
$var wire 2 > I [1:0] $end
$var wire 1 ? S $end
$var wire 1 @ Y $end
$var wire 1 A and_1 $end
$var wire 1 B and_2 $end
$var wire 1 C nots $end
$upscope $end
$scope module M2 $end
$var wire 2 D I [1:0] $end
$var wire 1 E S $end
$var wire 1 F Y $end
$var wire 1 G and_1 $end
$var wire 1 H and_2 $end
$var wire 1 I nots $end
$upscope $end
$scope module M3 $end
$var wire 2 J I [1:0] $end
$var wire 1 K S $end
$var wire 1 = Y $end
$var wire 1 L and_1 $end
$var wire 1 M and_2 $end
$var wire 1 N nots $end
$upscope $end
$upscope $end
$scope module M0 $end
$var wire 2 O I [1:0] $end
$var wire 1 P S $end
$var wire 1 $ Y $end
$var wire 1 Q and_1 $end
$var wire 1 R and_2 $end
$var wire 1 S nots $end
$upscope $end
$upscope $end
$upscope $end
$enddefinitions $end
$comment Show the parameter values. $end
$dumpall
$end
#0
$dumpvars
1S
0R
0Q
0P
b0 O
1N
0M
0L
0K
b0 J
1I
0H
0G
0F
0E
b0 D
1C
0B
0A
0@
0?
b0 >
0=
b0 <
b0 ;
b0 :
19
08
07
06
b0 5
14
03
02
01
00
b0 /
1.
0-
0,
0+
0*
b0 )
0(
b0 '
b0 &
b0 %
0$
b0 #
b0 "
b0 !
$end
#50
1$
1Q
b1 #
b1 O
1(
17
b1 '
b1 5
1+
0.
1-
04
0C
0I
1*
10
1?
1E
b11 )
b1 >
b1 D
b1 &
b1 ;
b11 %
b101 :
b1 "
b1010011 !
#100
0$
1=
0Q
1M
b10 #
b10 O
0(
1@
b11 <
b11 J
1F
1,
b1 '
b1 5
1+
07
1A
1G
1.
0-
14
09
1C
1I
0N
0*
00
16
0?
0E
1K
b10 &
b10 ;
b10 "
#150
1$
1Q
0=
b1 #
b1 O
1(
0M
18
0@
b0 <
b0 J
0F
0,
b11 '
b11 5
11
0A
0G
0.
1-
04
13
0C
0I
1*
10
1?
1E
b10 /
b11 &
b11 ;
b1011 %
b11 "
b1011011 !
#200
1R
1=
b10 #
b10 O
0(
1M
08
1@
b11 <
b11 J
1F
1,
1+
b1 '
b1 5
01
1A
1G
1$
1.
0-
14
03
1C
1I
0Q
0*
00
0?
0E
0S
b0 /
b11 D
b10 &
b10 ;
1P
b11 %
b1101 :
b110 "
b11010011 !
#250
0$
0R
b0 #
b0 O
0=
0M
0@
b0 <
b0 J
0F
0,
0A
0G
0.
1-
04
0C
0I
1*
10
1?
1E
b1 D
b11 &
b11 ;
b101 :
b111 "
b1010011 !
#300
1$
1R
1=
1L
b11 #
b11 O
1(
1@
b11 <
b11 J
1F
1,
b1 '
b1 5
1+
17
1A
1G
1.
0-
14
19
1C
1I
1N
0*
00
06
0?
0E
0K
b0 &
b0 ;
b100 "
#350
0$
0R
b1 #
b1 O
0=
0L
b10 <
b10 J
0@
0,
0A
0G
0.
1-
04
0C
0I
1H
1*
10
1?
1E
b11 D
b1 &
b1 ;
b1101 :
b101 "
b11010011 !
#400
1$
1R
0(
1@
1,
b1 '
b1 5
1+
07
1A
1G
b11 <
b11 J
1F
b10 #
b10 O
1=
1.
0-
14
09
1C
1I
0H
0N
1M
0*
00
16
0?
0E
1K
b11 >
b1 D
b10 &
b10 ;
b111 :
b110 "
b1110011 !
#450
0$
0R
b0 #
b0 O
0=
0M
0F
b0 <
b0 J
0@
0,
0G
0A
0.
1-
04
0C
0I
1*
10
1?
1E
b0 >
b11 &
b11 ;
b100 :
b111 "
b1000011 !
#500
1$
1Q
b1 #
b1 O
1(
b10 <
b10 J
1F
17
1H
19
1N
06
0K
1S
b1 >
b10 D
b1 &
b1 ;
0P
b1001 :
b1 "
b10010011 !
#550
0$
0Q
0(
07
b10 #
b10 O
1=
09
0N
1M
16
1K
b10 )
b0 >
b11 D
b11 &
b11 ;
b10 %
b1100 :
b11 "
b11000010 !
