0001001_3_to_8_Decoder_using_case_statement/3_to_8_decoder.v
//if input in demultiplexer is considered or connected to +5 v or logic 1, we can construct decoder... it was just relation between the two
//let's implement 3:8 decoder now
//3 inputs and as accoradence to input output will change

module three_to_eight_decoder(
    input [2:0] inp,
    output reg [7:0] out
);
    always @(*) begin
        out = 8'b00000000;
        out[inp] = 1'b1;
    end
endmodule

0001001_3_to_8_Decoder_using_case_statement/testbench.v
`timescale 10ns/1ns

module three_to_eight_decoder_tb;

    reg [2:0] inp;
    wire [7:0] out;

    three_to_eight_decoder uut(
        .inp(inp),
        .out(out)
    );

    initial begin
        $dumpfile("vcd_3_to_8.vcd");
        $dumpvars(0,uut);

        $monitor("Time : %0t | Input : %b | Output : %b",$time, inp, out);
        inp = 3'b000;
        //out = 8'b00000000;

        #10 inp = 3'b001;
        #10 inp = 3'b010;
        #10 inp = 3'b011;
        #10 inp = 3'b100;
        #10 inp = 3'b101;
        #10 inp = 3'b110;
        #10 inp = 3'b111;
        #10 $finish;
    end
endmodule

0001001__3_to_8_Decoder_using_case_statement/vcd_3_to_8.vcd
$date
	Thu Jun 12 13:24:32 2025
$end
$version
	Icarus Verilog
$end
$timescale
	1ns
$end
$scope module three_to_eight_decoder_tb $end
$scope module uut $end
$var wire 3 ! inp [2:0] $end
$var reg 8 " out [7:0] $end
$upscope $end
$upscope $end
$enddefinitions $end
$comment Show the parameter values. $end
$dumpall
$end
#0
$dumpvars
b1 "
b0 !
$end
#100
b10 "
b1 !
#200
b100 "
b10 !
#300
b1000 "
b11 !
#400
b10000 "
b100 !
#500
b100000 "
b101 !
#600
b1000000 "
b110 !
#700
b10000000 "
b111 !
