0010111__Shift_Register_Serial_In_Serial_Out/d_flipflop.v
module d_flipflop(
    input d,
    input clk,
    input rst,
    output reg q
);
    always @(posedge clk, posedge rst) begin
        if(rst) q<=1'b0;
        else q<=d;
    end
    
endmodule

0010111__Shift_Register_Serial_In_Serial_Out/register.v
module register(
    input d,
    input clk,
    input rst,
    output q
);
    wire [3:0] Q;
    assign q = Q[3];
    d_flipflop m1(
        .d(d),
        .clk(clk),
        .rst(rst),
        .q(Q[0])
    );
    
    d_flipflop m2(
        .d(Q[0]),
        .clk(clk),
        .rst(rst),
        .q(Q[1])
    );
    
    d_flipflop m3(
        .d(Q[1]),
        .clk(clk),
        .rst(rst),
        .q(Q[2])
    );
    
    d_flipflop m4(
        .d(Q[2]),
        .clk(clk),
        .rst(rst),
        .q(Q[3])
    );
    
    
endmodule

0010111__Shift_Register_Serial_In_Serial_Out/serial_register_SISO.v
//4-bit data storage will be done
module serial_register_SISO(
    input data,
    input clk,
    input rst,
    output Q
);
    register abc(
        .d(data),
        .clk(clk),
        .rst(rst),
        .q(Q)
    );

endmodule

0010111__Shift_Register_Serial_In_Serial_Out/serial_register_SISO_tb.v
`timescale 10ps/1ps
module serial_register_SISO_tb;
    reg clk, reset;
    reg data;
    wire Q;

    serial_register_SISO uut(
        .data(data),
        .clk(clk),
        .rst(reset),
        .Q(Q)
    );

    initial begin
        clk = 0;
        forever #20 clk = ~clk;
    end

    initial begin
        $dumpfile("vcd_file.vcd");
        $dumpvars(0,serial_register_SISO_tb);


        $monitor("Time : %0t | Clock : %b | Reset : %b | Data : %b | Q : %b",$time, clk, reset, data, Q);

         
        reset = 1; data = 0;
        @(posedge clk);  
        reset = 0;

        // Serial data input (bitstream): 1 0 1 0 0 0 1 1 1 0 1 1 0 1 1 0 1
        send_bit(1);
        send_bit(0);
        send_bit(1);
        send_bit(0);
        send_bit(0);
        send_bit(0);
        send_bit(1);
        send_bit(1);
        send_bit(1);
        send_bit(0);
        send_bit(1);
        send_bit(1);
        send_bit(0);
        send_bit(1);
        send_bit(1);
        send_bit(0);
        send_bit(1);

        @(posedge clk);
        $finish;
    end

    
    task send_bit(input reg bit_val);
        begin
            @(posedge clk);
            data = bit_val;
        end
    endtask

endmodule

0010111__Shift_Register_Serial_In_Serial_Out/vcd_file.vcd
$date
	Fri Jun 27 12:11:20 2025
$end
$version
	Icarus Verilog
$end
$timescale
	1ps
$end
$scope module serial_register_SISO_tb $end
$var wire 1 ! Q $end
$var reg 1 " clk $end
$var reg 1 # data $end
$var reg 1 $ reset $end
$scope module uut $end
$var wire 1 " clk $end
$var wire 1 # data $end
$var wire 1 $ rst $end
$var wire 1 ! Q $end
$scope module abc $end
$var wire 1 " clk $end
$var wire 1 # d $end
$var wire 1 $ rst $end
$var wire 1 ! q $end
$var wire 4 % Q [3:0] $end
$scope module m1 $end
$var wire 1 " clk $end
$var wire 1 # d $end
$var wire 1 $ rst $end
$var reg 1 & q $end
$upscope $end
$scope module m2 $end
$var wire 1 " clk $end
$var wire 1 ' d $end
$var wire 1 $ rst $end
$var reg 1 ( q $end
$upscope $end
$scope module m3 $end
$var wire 1 " clk $end
$var wire 1 ) d $end
$var wire 1 $ rst $end
$var reg 1 * q $end
$upscope $end
$scope module m4 $end
$var wire 1 " clk $end
$var wire 1 + d $end
$var wire 1 $ rst $end
$var reg 1 , q $end
$upscope $end
$upscope $end
$upscope $end
$scope task send_bit $end
$var reg 1 - bit_val $end
$upscope $end
$upscope $end
$enddefinitions $end
$comment Show the parameter values. $end
$dumpall
$end
#0
$dumpvars
x-
0,
0+
0*
0)
0(
0'
0&
b0 %
1$
0#
0"
0!
$end
#200
1-
0$
1"
#400
0"
#600
1'
b1 %
1&
0-
1#
1"
#800
0"
#1000
1)
0'
1(
b10 %
0&
1-
0#
1"
#1200
0"
#1400
1'
0)
1+
1&
0(
b101 %
1*
0-
1#
1"
#1600
0"
#1800
1!
0+
1)
0'
1,
0*
1(
b1010 %
0&
0#
1"
#2000
0"
#2200
0)
1+
0!
0(
1*
b100 %
0,
1"
#2400
0"
#2600
1!
0+
1,
b1000 %
0*
1-
1"
#2800
0"
#3000
1'
0!
1&
b1 %
0,
1#
1"
#3200
0"
#3400
1)
b11 %
1(
1"
#3600
0"
#3800
1+
b111 %
1*
0-
1"
#4000
0"
#4200
1!
0'
1,
b1110 %
0&
1-
0#
1"
#4400
0"
#4600
1'
0)
1&
b1101 %
0(
1#
1"
#4800
0"
#5000
0+
1)
0*
b1011 %
1(
0-
1"
#5200
0"
#5400
0'
1+
0!
0&
1*
b110 %
0,
1-
0#
1"
#5600
0"
#5800
1!
0)
1'
1,
0(
b1101 %
1&
1#
1"
#6000
0"
#6200
1)
0+
1(
b1011 %
0*
0-
1"
#6400
0"
#6600
0!
1+
0'
0,
1*
b110 %
0&
1-
0#
1"
#6800
0"
#7000
1'
0)
1!
1&
0(
b1101 %
1,
1#
1"
#7200
0"
#7400
0+
1)
0*
b1011 %
1(
1"
